speakin_short_vec_sdk
test
