Metadata-Version: 1.0
Name: speakin-short-vec-sdk
Version: 1.0.1
Summary: release_v1
Home-page: UNKNOWN
Author: UNKNOWN
Author-email: UNKNOWN
License: UNKNOWN
Keywords: Swagger,release_v1
Platform: UNKNOWN
